{
    "parent": "minecraft:recipes/root",
    "rewards": {
        "recipes": [
            "sophisticatedbackpacks:advanced_void_upgrade"
        ]
    },
    "criteria": {
        "has_void_upgrade": {
            "trigger": "minecraft:inventory_changed",
            "conditions": {
                "items": [
                    {
                        "item": "sophisticatedbackpacks:void_upgrade"
                    }
                ]
            }
        },
        "has_the_recipe": {
            "trigger": "minecraft:recipe_unlocked",
            "conditions": {
                "recipe": "sophisticatedbackpacks:advanced_void_upgrade"
            }
        }
    },
    "requirements": [
        [
            "has_void_upgrade",
            "has_the_recipe"
        ]
    ]
}